starlette_auth/__init__.py
starlette_auth/authentication.py
starlette_auth/py.typed
starlette_auth-0.2.3.dist-info/LICENSE
starlette_auth-0.2.3.dist-info/METADATA
starlette_auth-0.2.3.dist-info/WHEEL
starlette_auth-0.2.3.dist-info/RECORD
