Metadata-Version: 2.1
Name: starlette_auth
Version: 0.2.3
Summary: Authentication library for Starlette.
Home-page: https://github.com/alex-oleshkevich/starlette_auth
License: MIT
Author: Alex Oleshkevich
Author-email: alex.oleshkevich@gmail.com
Requires-Python: >=3.11,<4.0
Classifier: Development Status :: 5 - Production/Stable
Classifier: Environment :: Web Environment
Classifier: Intended Audience :: Developers
Classifier: License :: OSI Approved :: MIT License
Classifier: Operating System :: OS Independent
Classifier: Programming Language :: Python :: 3
Classifier: Programming Language :: Python :: 3.11
Classifier: Programming Language :: Python :: 3.12
Classifier: Programming Language :: Python :: 3.13
Classifier: Topic :: Software Development :: Libraries :: Python Modules
Classifier: Typing :: Typed
Provides-Extra: starsessions
Requires-Dist: itsdangerous (>=2.2.0,<3.0.0)
Requires-Dist: starlette
Requires-Dist: starsessions ; extra == "starsessions"
Project-URL: Documentation, https://github.com/alex-oleshkevich/starlette_auth
Project-URL: Repository, https://github.com/alex-oleshkevich/starlette_auth
